captivity/__init__.py
captivity/concat.py
captivity/merge.py
captivity/support/__init__.py
captivity/support/patch_default.py
captivity-0.1.2.dist-info/LICENSE
captivity-0.1.2.dist-info/METADATA
captivity-0.1.2.dist-info/WHEEL
captivity-0.1.2.dist-info/top_level.txt
captivity-0.1.2.dist-info/RECORD
