Metadata-Version: 2.1
Name: captivity
Version: 0.1.2
Summary: Cages in Pandas
Home-page: https://github.com/maxsnijders/captivity
Author: Max Snijders
Author-email: max@msnijders.com
License: UNKNOWN
Platform: UNKNOWN
Requires-Dist: methodtools (==0.1.2)
Requires-Dist: pyyaml (==5.3.1)
